rocketsimu/__init__.py
rocketsimu/grain.py
rocketsimu/motorsimu.py
rocketsimu/nozzle.py
rocketsimu/propellent.py
rocketsimu-1.0.5.dist-info/LICENSE
rocketsimu-1.0.5.dist-info/METADATA
rocketsimu-1.0.5.dist-info/WHEEL
rocketsimu-1.0.5.dist-info/top_level.txt
rocketsimu-1.0.5.dist-info/RECORD
