Metadata-Version: 2.1
Name: rocketsimu
Version: 1.0.5
Summary: Simple tool for rocket simulation by python, the code were based on the original SRD  (Simple Rccket Designer)
Home-page: https://zqwei-quix.ukgsdn.co.uk/simple-rocket-designer/
Author: Quix Fan @ZQWEI-Tech
Author-email: qxdnfsy@126.com
License: MIT
Platform: UNKNOWN
Classifier: Programming Language :: Python :: 3
Classifier: License :: OSI Approved :: MIT License
Classifier: Operating System :: OS Independent
Requires-Dist: numpy
Requires-Dist: scipy
